mahiru/core/__init__.py
mahiru/core/event.py
mahiru/core/module.py
mahiru_core-0.0.2.dist-info/METADATA
mahiru_core-0.0.2.dist-info/WHEEL
mahiru_core-0.0.2.dist-info/top_level.txt
mahiru_core-0.0.2.dist-info/RECORD
