Metadata-Version: 2.1
Name: mahiru_core
Version: 0.0.2
Summary: Shared core classes of Mahiru
Home-page: https://gitlab.com/henny022/mahiru/core
Author: Henny022
Author-email: hen.geheim22@gmail.com
License: Unlicense
Platform: UNKNOWN
Classifier: License :: OSI Approved :: The Unlicense (Unlicense)
Classifier: Programming Language :: Python :: 3
Classifier: Programming Language :: Python :: 3.7
Requires-Python: >=3.7
